kconfgen/__init__.py
kconfgen/cli.py
kconfgen/core.py
kconfgen-1.2.2.dist-info/LICENSE
kconfgen-1.2.2.dist-info/METADATA
kconfgen-1.2.2.dist-info/WHEEL
kconfgen-1.2.2.dist-info/entry_points.txt
kconfgen-1.2.2.dist-info/top_level.txt
kconfgen-1.2.2.dist-info/RECORD
