Metadata-Version: 2.1
Name: kconfgen
Version: 1.2.2
Summary: A generator of (minimal) Linux kernel configuration files.
Home-page: https://github.com/rbarrois/kconfgen
Author: Raphaël Barrois
Author-email: raphael.barrois+kconfgen@polytechnique.org
License: MIT
Keywords: kconfgen,kconfig,kernel,linux,configuration,generator
Platform: UNKNOWN
Classifier: Development Status :: 5 - Production/Stable
Classifier: Intended Audience :: Developers
Classifier: License :: OSI Approved :: MIT License
Classifier: Operating System :: OS Independent
Classifier: Programming Language :: Python
Classifier: Programming Language :: Python :: 3.6
Classifier: Programming Language :: Python :: 3.7
Classifier: Programming Language :: Python :: 3.8
Requires-Python: >=3.5
Requires-Dist: kconfiglib
Requires-Dist: toml
